{"id":"Metallica - Low Mans Lyric","name":"Low Mans Lyric","artist":"Metallica","url":"metallica_low_mans_lyric.json","versions":[{"id":"Metallica - Low Mans Lyric - Chords + lyrics","name":"Chords + lyrics","instrument":"guitar","tuning":"Half-Step Down","duration":300,"content":"\n\t\t\t[Intro/Verse]\n\n\t\t\tRiff 1\n\t\t\t\t A               G6               D2              E       G\n\t\t\tD#|-------0-----------------0--------------0------------0-------0--------|\n\t\t\tA#|---------2----------------2-----------3---3------------0-------0------|\n\t\t\tF#|------------2----------------0------2---------2-----------------------|\n\t\t\tC#|---2------------------0-----------0-----------------------------------|\n\t\t\tG#|-0------------------2-------------------------------------------------|\n\t\t\tD#|-----------------3--------------------------------0-------3-----------|\n\n\t\t\t  My eyes       seek reality\n\t\t\t  \n\t\t\t  My fingers feel for faith\n\n\t\t\t  Touch clean with a dirty hand\n\n\t\t\t  I touched the clean through the waste\n\t\t\t\n\t\t\t[Pre-Chorus]\n\t\t\t(Riff 2)\n\t\t\tAm                Em\n\t\t\tThe trash fire is warm\n\t\t\tAm                        Em\n\t\t\tBut nowhere safe from the storm\n\t\t\tAm                  G\n\t\t\tAnd I can't bear to see\n\t\t\t\t\t\t\t C\n\t\t\tWhat I've let me be\n\t\t\t\t\t\t  B\n\t\t\tSo wicked and worn\n\t\t\t\n\t\t\t[Chorus]\n\t\t\tAm               Em\n\t\t\tSo as I write to you\n\t\t\tAm                     Em\n\t\t\tOf what is done and to do\n\t\t\tAm                G\n\t\t\tMaybe you'll understand\n\t\t\t\t\t\t\t\t   C\n\t\t\tAnd won't cry for this man\n\t\t\t\t\t\t\t B                B\n\t\t\tcause low man is due              please forgive me!!!!\n\t\t\t\n\t\t\t\n\t\t\tA  \tG6 \tD2 \tE G\n\n\t\t\tMy eyes seek reality\n\t\t\tMy fingers feel for faith\n\t\t\tTouch clean with a dirty hand\n\t\t\tI touched the clean to the waste\n\n\n\t\t\tThe trash fire is warm\n\t\t\tBut nowhere safe from the storm\n\t\t\tAnd I can't bare to see\n\t\t\tWhat I've let me be\n\t\t\tSo wicked and worn\n\n\t\t\tSo as I write to you, yeah\n\t\t\tOf what is done and to do\n\t\t\tMaybe you'll understand\n\t\t\tAnd won't cry for this man\n\t\t\t'Cause low man is due\n\t\t\tPlease forgive me\n\t\t\tPlease forgive me\n\t\t\tPlease forgive me\n\t\t\t\n\t\t\tRiff 3\n\t\t\tAm    Am-    F\n\n\t\t\tSo low the sky is all I see\n\t\t\tAll I want from you is forgive me\n\t\t\tSo you bring this poor dog in from the rain\n\t\t\tThough he just wants right back out again\n\t\t\t\n\t\t\tAnd I cry, to the alley way\n\t\t\tConfess all to the rain\n\t\t\tBut I lie, lie straight to the mirror\n\t\t\tThe one I've broken, to match my face\n\t\t\t\n\t\t\tThe trash fire is warm\n\t\t\tBut nowhere safe from the storm\n\t\t\tAnd I can't bare to see\n\t\t\tWhat I've let me be\n\t\t\tSo wicked and worn\n\t\t\tSo as I write to you\n\t\t\tOf what is done and to do\n\t\t\tMaybe you'll understand\n\t\t\tAnd won't cry for this man\n\t\t\t'Cause low man is due\n\t\t\tPlease forgive me\n\t\t\tPlease forgive me\n\n\t\t\tAm  Am-  F\n\t\t\tSo low the sky is all I see\n\t\t\tAll I want from you is forgive me\n\t\t\tSo you bring this poor dog in from the rain\n\t\t\tThough he just wants right back out again\n\n\t\t\t[finger-picking, same as intro]\n\t\t\tA\tG6\tD2\tE \tG\n\t\t\tMy eyes seek reality\n\t\t\tMy fingers seek my veins\n"}]}