{"id":"Pink Floyd - Pigs On The Wing","name":"Pigs On The Wing","artist":"Pink Floyd","url":"pink_floyd_pigs_on_the_wing.json","versions":[{"id":"Pink Floyd - Pigs On The Wing - Chords + lyrics","name":"Chords + lyrics","instrument":"guitar","tuning":"Standard","content":"\nPink Floyd - Pigs On The Wing (Part One) (Waters)\nG  C  G\n[Verse 1]\nG              C   Csus4  C                   G  Gsus4  G\nIf you didn't care           what happened to me\n     C    Csus4  C        G   Gsus4  G\nAnd I didn't care           for you\n A                           A7\nWe would zig-zag our way through the boredom and pain\nG          C        D              G\nOccasionally glancing up through the rain\nAm        F            Am                F  C  C/B Am\nWondering which of the buggers to blame\nD        Dsus4   D                  G\nAnd watching             for pig on the wing\nPink Floyd - Pigs On The Wing (Part Two) (Waters)\nG  C  G\n[Verse 2]\nG                C    Csus4  C                     G    Gsus4  G\nYou know that I care             what happens to you\n\n            C    Csus4  C           G     Gsus4  G\nAnd I know that you care           for me too\nA                        A7\nSo I don't feel alone or the weight of the stone\nG                   C                 D      G\nNow that I've found somewhere safe to bury my bone\nAm       F       Am              F      C C/B Am\nAnd any fool knows     a dog needs a home\nD       Dsus4  D                       G\nA shelter               from pigs on the wing"}]}